{
  "hash": "f98ca31a",
  "configHash": "8492cda5",
  "lockfileHash": "92809324",
  "browserHash": "15d0b2b4",
  "optimized": {
    "react": {
      "src": "../../node_modules/react/index.js",
      "file": "react.js",
      "fileHash": "e47620f3",
      "needsInterop": true
    },
    "react-dom/client": {
      "src": "../../node_modules/react-dom/client.js",
      "file": "react-dom_client.js",
      "fileHash": "55b32d5c",
      "needsInterop": true
    }
  },
  "chunks": {
    "chunk-GFWMZNU4": {
      "file": "chunk-GFWMZNU4.js"
    }
  }
}